coupeutils/__init__.py
coupeutils/firestore.py
coupeutils/gcs.py
coupeutils/llm.py
coupeutils/queue_utils.py
coupeutils/weaviate.py
coupeutils/web.py
coupeutils-0.0.38.dist-info/LICENSE.txt
coupeutils-0.0.38.dist-info/METADATA
coupeutils-0.0.38.dist-info/WHEEL
coupeutils-0.0.38.dist-info/top_level.txt
coupeutils-0.0.38.dist-info/RECORD
