Metadata-Version: 2.1
Name: coupeutils
Version: 0.0.38
Summary: Library with utilities for projects.
Home-page: https://github.com/teossaurus/coupe-utils-library
Author: Teo Soares
Author-email: hello@teo.works
License: MIT
License-File: LICENSE.txt
Requires-Dist: annotated-types
Requires-Dist: anthropic
Requires-Dist: anyio
Requires-Dist: attrs
Requires-Dist: Authlib
Requires-Dist: beautifulsoup4
Requires-Dist: bs4
Requires-Dist: cachetools
Requires-Dist: certifi
Requires-Dist: cffi
Requires-Dist: charset-normalizer
Requires-Dist: cryptography
Requires-Dist: distro
Requires-Dist: docstring-parser
Requires-Dist: exceptiongroup
Requires-Dist: filelock
Requires-Dist: filetype
Requires-Dist: fsspec
Requires-Dist: google-api-core
Requires-Dist: google-auth
Requires-Dist: google-cloud-aiplatform
Requires-Dist: google-cloud-bigquery
Requires-Dist: google-cloud-core
Requires-Dist: google-cloud-firestore
Requires-Dist: google-cloud-resource-manager
Requires-Dist: google-cloud-storage
Requires-Dist: google-cloud-tasks
Requires-Dist: google-crc32c
Requires-Dist: google-resumable-media
Requires-Dist: googleapis-common-protos
Requires-Dist: grpc-google-iam-v1
Requires-Dist: grpcio
Requires-Dist: grpcio-health-checking
Requires-Dist: grpcio-status
Requires-Dist: grpcio-tools
Requires-Dist: h11
Requires-Dist: httpcore
Requires-Dist: httpx
Requires-Dist: huggingface-hub
Requires-Dist: idna
Requires-Dist: jiter
Requires-Dist: json5
Requires-Dist: numpy
Requires-Dist: openai
Requires-Dist: outcome
Requires-Dist: packaging
Requires-Dist: proto-plus
Requires-Dist: protobuf
Requires-Dist: pyasn1
Requires-Dist: pyasn1-modules
Requires-Dist: pycparser
Requires-Dist: pydantic
Requires-Dist: pydantic-core
Requires-Dist: PySocks
Requires-Dist: python-dateutil
Requires-Dist: PyYAML
Requires-Dist: requests
Requires-Dist: rsa
Requires-Dist: selenium
Requires-Dist: shapely
Requires-Dist: six
Requires-Dist: sniffio
Requires-Dist: sortedcontainers
Requires-Dist: soupsieve
Requires-Dist: tokenizers
Requires-Dist: tqdm
Requires-Dist: trio
Requires-Dist: trio-websocket
Requires-Dist: typing-extensions
Requires-Dist: urllib3
Requires-Dist: validators
Requires-Dist: vertexai
Requires-Dist: weaviate-client
Requires-Dist: websocket-client
Requires-Dist: wsproto
